untitled_job_runner/__init__.py
untitled_job_runner/job.py
untitled_job_runner/runner.py
untitled_job_runner-0.0.3.dist-info/LICENSE
untitled_job_runner-0.0.3.dist-info/METADATA
untitled_job_runner-0.0.3.dist-info/WHEEL
untitled_job_runner-0.0.3.dist-info/top_level.txt
untitled_job_runner-0.0.3.dist-info/RECORD
