Metadata-Version: 2.1
Name: untitled-job-runner
Version: 0.0.3
Summary: It runs things!
Home-page: https://github.com/QUT-Digital-Observatory/untitled_job_runner/
Author: QUT Digital Observatory
Author-email: digitalobservatory@qut.edu.au
License: MIT
Platform: UNKNOWN
Classifier: Programming Language :: Python :: 3
Classifier: Operating System :: OS Independent
Classifier: Development Status :: 3 - Alpha
Classifier: Intended Audience :: Developers
Classifier: Intended Audience :: Science/Research
Classifier: License :: OSI Approved :: MIT License
Requires-Python: >=3.6
Requires-Dist: Pebble (>=4.5.3)
Provides-Extra: development
Requires-Dist: nox ; extra == 'development'
Requires-Dist: pytest ; extra == 'development'
Requires-Dist: pre-commit ; extra == 'development'
